lexicase/__init__.py
lexicase/dispatch.py
lexicase/numpy_impl.py
lexicase/utils.py
lexicase-0.3.0.dist-info/licenses/LICENSE
lexicase-0.3.0.dist-info/METADATA
lexicase-0.3.0.dist-info/WHEEL
lexicase-0.3.0.dist-info/top_level.txt
lexicase-0.3.0.dist-info/RECORD
