Metadata-Version: 2.4
Name: lexicase
Version: 0.3.0
Summary: Fast, vectorized lexicase selection in NumPy for evolutionary computation
Author: Ryan Bahlous-Boldi
License-Expression: MIT
Project-URL: Homepage, https://github.com/ryanboldi/lexicase
Project-URL: Repository, https://github.com/ryanboldi/lexicase
Project-URL: Issues, https://github.com/ryanboldi/lexicase/issues
Keywords: evolutionary-computation,genetic-algorithms,selection,lexicase
Classifier: Development Status :: 4 - Beta
Classifier: Intended Audience :: Science/Research
Classifier: Programming Language :: Python :: 3
Classifier: Programming Language :: Python :: 3.8
Classifier: Programming Language :: Python :: 3.9
Classifier: Programming Language :: Python :: 3.10
Classifier: Programming Language :: Python :: 3.11
Classifier: Programming Language :: Python :: 3.12
Classifier: Topic :: Scientific/Engineering :: Artificial Intelligence
Requires-Python: >=3.8
License-File: LICENSE
Requires-Dist: numpy>=1.20.0
Provides-Extra: dev
Requires-Dist: pytest; extra == "dev"
Requires-Dist: pytest-cov; extra == "dev"
Dynamic: license-file
